clarity/__init__.py
clarity/enums.py
clarity/parsers.py
crud.py
sjcli.py
tests/__init__.py
tests/decorators_test.py
tests/mocks/mock_app-access.log
tests/mocks/mock_test.csv
tests/mocks/mock_test.json
tests/mocks/mock_timestamp_col0_test.csv
tests/mocks/mock_timestamp_test.csv
tests/mocks/mock_timestamp_test_1csv
tests/parsers_test.py
tests/sjcli_test.py
tests/sjcli_utils_file_helpers_csv_test.py
tests/sjcli_utils_file_helpers_json_test.py
tests/utilities.py
tests/utils_helpers_test.py
utils/__init__.py
utils/decorators.py
utils/enums.py
utils/file_helpers.py
utils/helpers.py
sjcli-1.0.4.dist-info/METADATA
sjcli-1.0.4.dist-info/WHEEL
sjcli-1.0.4.dist-info/entry_points.txt
sjcli-1.0.4.dist-info/RECORD
